aspose/__init__.py
aspose/page.cp310-win32.pyd
aspose/page.cp311-win32.pyd
aspose/page.cp312-win32.pyd
aspose/page.cp313-win32.pyd
aspose/page.cp36-win32.pyd
aspose/page.cp37-win32.pyd
aspose/page.cp38-win32.pyd
aspose/page.cp39-win32.pyd
aspose/pycore.cp310-win32.pyd
aspose/pycore.cp311-win32.pyd
aspose/pycore.cp312-win32.pyd
aspose/pycore.cp313-win32.pyd
aspose/pycore.cp36-win32.pyd
aspose/pycore.cp37-win32.pyd
aspose/pycore.cp38-win32.pyd
aspose/pycore.cp39-win32.pyd
aspose/pydrawing.cp310-win32.pyd
aspose/pydrawing.cp311-win32.pyd
aspose/pydrawing.cp312-win32.pyd
aspose/pydrawing.cp313-win32.pyd
aspose/pydrawing.cp36-win32.pyd
aspose/pydrawing.cp37-win32.pyd
aspose/pydrawing.cp38-win32.pyd
aspose/pydrawing.cp39-win32.pyd
aspose/pygc.cp310-win32.pyd
aspose/pygc.cp311-win32.pyd
aspose/pygc.cp312-win32.pyd
aspose/pygc.cp313-win32.pyd
aspose/pygc.cp36-win32.pyd
aspose/pygc.cp37-win32.pyd
aspose/pygc.cp38-win32.pyd
aspose/pygc.cp39-win32.pyd
aspose/pyreflection.cp310-win32.pyd
aspose/pyreflection.cp311-win32.pyd
aspose/pyreflection.cp312-win32.pyd
aspose/pyreflection.cp313-win32.pyd
aspose/pyreflection.cp36-win32.pyd
aspose/pyreflection.cp37-win32.pyd
aspose/pyreflection.cp38-win32.pyd
aspose/pyreflection.cp39-win32.pyd
aspose/__pyinstaller/__init__.pyi
aspose/__pyinstaller/hook-aspose.py
aspose/assemblies/page/Aspose.Page.dll
aspose/assemblies/page/Microsoft.Win32.SystemEvents.dll
aspose/assemblies/page/System.Drawing.Common.dll
aspose/assemblies/page/System.Security.AccessControl.dll
aspose/assemblies/page/System.Security.Permissions.dll
aspose/assemblies/page/System.Security.Principal.Windows.dll
aspose/assemblies/page/System.Windows.Extensions.dll
aspose/assemblies/page/WrpInterop.Aspose.Page.dll
aspose/assemblies/pycore/WrpInterop.Aspose.PyCore.dll
aspose/assemblies/pydrawing/Microsoft.Win32.SystemEvents.dll
aspose/assemblies/pydrawing/System.Drawing.Common.dll
aspose/assemblies/pydrawing/WrpInterop.Aspose.PyDrawing.dll
aspose/assemblies/pygc/Aspose.PyGC.dll
aspose_page-25.8.0.dist-info/METADATA
aspose_page-25.8.0.dist-info/WHEEL
aspose_page-25.8.0.dist-info/entry_points.txt
aspose_page-25.8.0.dist-info/top_level.txt
aspose_page-25.8.0.dist-info/RECORD
