Metadata-Version: 2.1
Name: aspose-page
Version: 25.8.0
Summary: Aspose.Page for Python via .NET makes your Python Apps instantly support to work with XPS, EPS/PS documents without installing any 3rd party software. It helps developers create/edit XPS documents while working with canvas, paths, and glyph elements. Utilize a set of primitives, such as, elliptical arcs, straights lines, Bezier curve segments to create vector graphics. Add default print tickets and preserve them in the XPS file. Link print ticket objects among job/document/page.
Home-page: https://products.aspose.com/page/python-net/
Author: Aspose
License: Other/Proprietary License
Project-URL: Blog, https://blog.aspose.com/categories/aspose.page-product-family/
Project-URL: Demos, https://products.aspose.app/page/family/
Project-URL: Docs, https://docs.aspose.com/page/python-net/
Project-URL: Free Support, https://forum.aspose.com/c/page/
Project-URL: API Reference, https://reference.aspose.com/page/python-net/
Project-URL: Temporary License, https://purchase.aspose.com/temporary-license/
Keywords: Aspose.Page PS EPS XPS OXPS PostScript PDF convert conversion ps-to-pdf ps-to-png ps-to-jpg ps-to-tiff ps-to-bmp eps-to-pdf eps-to-png eps-to-jpg eps-to-tiff eps-to-bmp xps-to-pdf xps-to-png xps-to-jpg xps-to-tiff xps-to-bmp sign-XPS eSign electronic signature Windows macOS Linux postscript-to-pdf postscript-to-png bulk Library Aspose.Total
Platform: win32
Classifier: Development Status :: 5 - Production/Stable
Classifier: Intended Audience :: Developers
Classifier: Intended Audience :: Education
Classifier: License :: Other/Proprietary License
Classifier: Operating System :: Microsoft :: Windows
Classifier: Operating System :: POSIX :: Linux
Classifier: Operating System :: Unix
Classifier: Programming Language :: Python :: 3 :: Only
Classifier: Programming Language :: Python :: 3.6
Classifier: Programming Language :: Python :: 3.7
Classifier: Programming Language :: Python :: 3.8
Classifier: Programming Language :: Python :: 3.9
Classifier: Programming Language :: Python :: 3.10
Classifier: Programming Language :: Python :: 3.11
Classifier: Programming Language :: Python :: 3.12
Classifier: Programming Language :: Python :: 3.13
Classifier: Topic :: Software Development
Classifier: Topic :: Software Development :: Libraries
Classifier: Topic :: Office/Business
Classifier: Topic :: Office/Business :: Office Suites
Requires-Python: >=3.6,<3.14
